{

	"menuRow" : {
		"rightImage" : "images/children.png",
		"height" : 44
	},
	
	"menuLabel" : {
		"left" : 60,
		"font" : {
			"fontSize" : 18,
			"fontWeight" : "bold"
		},
		"color" : "#CCCCCC",
		"minimumFontSize" : 12
	},

	"menuLeftImage" : {
		"left" : 7
	},
	
	"serverAddressLabelOnline" : {
		"left" : 10,
		"top" : 140,
		"font" : {
			"fontSize" : 13,
			"fontWeight" : "bold"
		},
		"color" : "#CCCCCC",
		"minimumFontSize" : 12
	},
	
	"serverAddressInputOnline" : {
		"left" : 10,
		"right" : 50,
		"top" : 160,
		"font" : {
			"fontSize" : 14
		},
		"minimumFontSize" : 12
	},
	
	"serverAddressHistoryButtonOnline" : {
		"right" : 10,
		"top" : 160,
		"width" : 32,
		"height" : 32,
		"backgroundImage" : "images/button_small.png",
		"backgroundLeftCap" : 9,
		"backgroundTopCap" : 32,
		"tintColor" : "#CCCCCC"
	},
	
	"serverAddressLabelSafari" : {
		"left" : 10,
		"top" : 285,
		"font" : {
			"fontSize" : 13,
			"fontWeight" : "bold"
		},
		"color" : "#CCCCCC",
		"minimumFontSize" : 12
	},
	
	"serverAddressInputSafari" : {
		"left" : 10,
		"right" : 50,
		"top" : 305,
		"font" : {
			"fontSize" : 14
		},
		"minimumFontSize" : 12
	},
	
	"serverAddressHistoryButtonSafari" : {
		"right" : 10,
		"top" : 305,
		"width" : 32,
		"height" : 32,
		"backgroundImage" : "images/button_small.png",
		"backgroundLeftCap" : 9,
		"backgroundTopCap" : 32,
		"tintColor" : "#CCCCCC"
	},

	"credentialsLabel" : {
		"left" : 10,
		"top" : 205,
		"font" : {
			"fontSize" : 13,
			"fontWeight" : "bold"
		},
		"color" : "#CCCCCC",
		"minimumFontSize" : 12
	},
	
	"usernameInput" : {
		"left" : 10,
		"right" : 10,
		"top" : 225,	
		"font" : {
			"fontSize" : 14
		},
		"minimumFontSize" : 12
	},
	
	"passwordInput" : {
		"left" : 10,
		"right" : 10,
		"top" : 265,
		"font" : {
			"fontSize" : 14
		},
		"minimumFontSize" : 12
	},
	
	"saveCredentialsSwitch" : {
		"right" : 10,
		"top" : 305
	},
	
	"saveCredentialsLabel" : {
		"left" : 10,
		"top" : 312,
		"font" : {
			"fontSize" : 13,
			"fontWeight" : "bold"
		},
		"color" : "#CCCCCC",
		"minimumFontSize" : 12
	},
	
	"loginButton" : {
		"left" : 10,
		"right" : 10,
		"top" : 350,
		"height" : 42,
		"color" : "#CCCCCC",
		"backgroundImage" : "images/button.png",
		"backgroundLeftCap" : 12,
		"backgroundTopCap" : 40
	},
	
	"watermarkOnline" : {
		"image" : "images/logo_small.png",
		"top" : 55
	},
	
	"watermarkOfflineSafari" : {
		"image" : "images/logo_big.png",
		"top" : 90
	},
	
	"infoButton" : {
		"color" : "#CCCCCC",
		"tintColor" : "#CCCCCC"		
	},

	"window" : {
		"opacity" : 1,
		"backgroundColor" : "#2B2B2B"
	},
	
	"jukeboxRewind" : {
		"width":38,
		"height":38,
		"bottom":0,
		"left":34,
		"image" : "images/back.png"
	},

	"jukeboxRewindGlow" : {
		"bottom":19,
		"left":53
	},

	"jukeboxPlayPause" : {
		"width":38,
		"height":38,
		"bottom":0,
		"left":105,
		"image" : "images/play.png"
	},

	"jukeboxPlayPauseGlow" : {
		"bottom":19,
		"left":124
	},

	"jukeboxForward" : {
		"width":38,
		"height":38,
		"bottom":0,
		"right":105,
		"image" : "images/forward.png"
	},

	"jukeboxForwardGlow" : {
		"bottom":19,
		"right":124
	},

	"jukeboxShuffle" : {
		"width":38,
		"height":38,
		"bottom":0,
		"right":34,
		"image" : "images/shuffle.png"
	},
	
	"jukeboxShuffleGlow" : {
		"bottom":19,
		"right":53
	},
	
	"appInfoTitle" : {
		"top" : 70,
		"font" : {
			"fontSize" : 25
		}
	},

	"appInfoVersion" : {
		"top" : 110,
		"font" : {
			"fontSize" : 15
		}
	},

	"appInfoTimestamp" : {
		"top" : 130,
		"font" : {
			"fontSize" : 12
		}
	},

	"appInfoLogo" : {
		"image" : "images/logo_big.png",
		"top" : 170
	},

	"appInfoCopyright" : {
		"top" : 340,
		"font" : {
			"fontSize" : 15
		}
	},

	"appInfoDesign1" : {
		"top" : 390,
		"font" : {
			"fontSize" : 15
		}
	},

	"appInfoDesign2" : {
		"top" : 410,
		"font" : {
			"fontSize" : 15
		}
	},
	
	"busyViewMessage1" : {
		"top" : 80,
		"font" : {
			"fontSize" : 15
		}
	},

	"busyViewMessage2" : {
		"top" : 110,
		"font" : {
			"fontSize" : 17
		}
	},

	"busyViewLogo" : {
		"image" : "images/logo_big.png",
		"top" : 170
	},
	
	"busyViewProgress" : {
		"top" : 350,
		"width" : 250,
		"min" : 0,
		"max" : 100,
		"value" : 0
	},
	
	"iad" : {
		"height" : 50,
		"bottom" : 0
	},
	
	"iadSpacing" : {
		"bottom" : 50
	},
	
	"settingsRow" : {
		"height" : 40
	},

	"jukeboxProgressBar" : {
		"bottom" : 60,
		"left" : 60,
		"right" : 60,
		"height" : 10
	},
	
	"jukeboxProgressPlayed" : {
		"bottom" : 60,
		"left" : 10,
		"height" : 10,
		"width" : 40,
		"font": {
			"fontSize" : 12
		},
		"textAlign" : "right",
		"color" : "#CCCCCC"
	},
	
	"jukeboxProgressRemaining" : {
		"bottom" : 60,
		"right" : 10,
		"width" : 40,
		"height" : 10,
		"font" : {
			"fontSize" : 12
		},
		"color" : "#CCCCCC"
	},
	
	"jukeboxActivityIndicator" : {
		"top" : 45,
		"left" : 0,
		"bottom" : 38,
		"right" : 0,
		"backgroundColor" : "#000000",
		"opacity" : 0.8,
		"visible" : false
	}
}
